{
  "city": "Saint-Étienne",
  "country": "France",
  "note": "Curated recurring highlights at real Saint-Étienne venues. Dates are relative to today. Each item links to an official source.",
  "events": [
    {
      "title": "Cité du Design – Biennale Hub",
      "category": "culture",
      "venue": "Cité du Design",
      "latitude": 45.4395,
      "longitude": 4.387,
      "is_outdoor": false,
      "day_offset": 2,
      "duration_days": 14,
      "description": "Design centre in a converted weapons factory — biennale events.",
      "source_name": "citedudesign.com",
      "source_url": "https://www.citedudesign.com/",
      "keyword": "Design"
    },
    {
      "title": "Musée d'Art Moderne et Contemporain",
      "category": "culture",
      "venue": "MAMC+",
      "latitude": 45.439,
      "longitude": 4.385,
      "is_outdoor": false,
      "day_offset": 3,
      "duration_days": 14,
      "description": "One of France's leading collections of modern and contemporary art.",
      "source_name": "mamc.saint-etienne.fr",
      "source_url": "https://www.mamc.saint-etienne.fr/",
      "keyword": "Museum"
    },
    {
      "title": "Stade Geoffroy-Guichard – Stadium Tour",
      "category": "sports",
      "venue": "Stade Geoffroy-Guichard",
      "latitude": 45.4608,
      "longitude": 4.392,
      "is_outdoor": false,
      "day_offset": 6,
      "duration_days": 1,
      "description": "Legendary 'Chaudron' football stadium tours and match days.",
      "source_name": "asse.fr",
      "source_url": "https://www.asse.fr/",
      "keyword": "Stadium"
    },
    {
      "title": "Parc de l'Europe – Lakeside Walk",
      "category": "nature",
      "venue": "Parc de l'Europe",
      "latitude": 45.428,
      "longitude": 4.4,
      "is_outdoor": true,
      "day_offset": 1,
      "duration_days": 1,
      "description": "Urban park with lake, trails and outdoor sports facilities.",
      "source_name": "saint-etienne.fr",
      "source_url": "https://www.saint-etienne.fr/",
      "keyword": "Park"
    },
    {
      "title": "Opéra-Théâtre – Performance Night",
      "category": "culture",
      "venue": "Opéra-Théâtre",
      "latitude": 45.4398,
      "longitude": 4.3875,
      "is_outdoor": false,
      "day_offset": 5,
      "duration_days": 1,
      "description": "Opera, theatre and dance in the city centre.",
      "source_name": "opera-theatre.saint-etienne.fr",
      "source_url": "https://www.opera-theatre.saint-etienne.fr/",
      "keyword": "Theatre"
    },
    {
      "title": "Musée de la Mine – Industrial Heritage",
      "category": "culture",
      "venue": "Musée de la Mine",
      "latitude": 45.42,
      "longitude": 4.41,
      "is_outdoor": false,
      "day_offset": 4,
      "duration_days": 7,
      "description": "Coal mining history in a preserved pithead and lamp room.",
      "source_name": "museedelamine.fr",
      "source_url": "https://www.museedelamine.fr/",
      "keyword": "Museum"
    },
    {
      "title": "Crêt de Roc – Panoramic Hike",
      "category": "nature",
      "venue": "Crêt de Roc",
      "latitude": 45.48,
      "longitude": 4.42,
      "is_outdoor": true,
      "day_offset": 7,
      "duration_days": 1,
      "description": "Remarkable rock formations and views over the Pilat foothills.",
      "source_name": "saint-etienne-metropole.fr",
      "source_url": "https://www.saint-etienne-metropole.fr/",
      "keyword": "Hike"
    },
    {
      "title": "Marché Fourière – Local Producers",
      "category": "markets",
      "venue": "Marché Fourière",
      "latitude": 45.438,
      "longitude": 4.389,
      "is_outdoor": true,
      "day_offset": 8,
      "duration_days": 1,
      "description": "Daily market for fruit, cheese and regional specialities.",
      "source_name": "saint-etienne.fr",
      "source_url": "https://www.saint-etienne.fr/",
      "keyword": "Market"
    },
    {
      "title": "Zénith Saint-Étienne – Concert",
      "category": "music",
      "venue": "Zénith",
      "latitude": 45.46,
      "longitude": 4.435,
      "is_outdoor": false,
      "day_offset": 9,
      "duration_days": 1,
      "description": "Major arena concerts south of the city centre.",
      "source_name": "zenithsaintetienne.com",
      "source_url": "https://www.zenithsaintetienne.com/",
      "keyword": "Concert"
    }
  ]
}
